autodropstack/__init__.py
autodropstack/autodropstack.py
autodropstack-1.1.0.dist-info/LICENSE
autodropstack-1.1.0.dist-info/METADATA
autodropstack-1.1.0.dist-info/WHEEL
autodropstack-1.1.0.dist-info/top_level.txt
autodropstack-1.1.0.dist-info/RECORD
