Metadata-Version: 2.1
Name: autodropstack
Version: 1.1.0
Summary: filo stack
Author: thearyadev
License-File: LICENSE
